pypn.py
pypn-0.9.dist-info/DESCRIPTION.rst
pypn-0.9.dist-info/METADATA
pypn-0.9.dist-info/RECORD
pypn-0.9.dist-info/WHEEL
pypn-0.9.dist-info/metadata.json
pypn-0.9.dist-info/top_level.txt
