Metadata-Version: 1.1
Name: pypn
Version: 0.9
Summary: Abstraction library to send push notifications through APNs, GCM and OneSignal
Home-page: https://github.com/alej0varas/pypn
Author: Alexandre Varas
Author-email: alej0varas@gmail.com
License: GNU Library or Lesser General Public License (LGPL)
Keywords: push notification notifications apns gcm onesignal google apple
Platform: UNKNOWN
Classifier: Development Status :: 4 - Beta
Classifier: Intended Audience :: Developers
Classifier: License :: OSI Approved :: GNU Library or Lesser General Public License (LGPL)
Classifier: Operating System :: OS Independent
Classifier: Topic :: Software Development :: Libraries
Classifier: Programming Language :: Python
Classifier: Programming Language :: Python :: 3.5
